waha/__init__.py
waha/client.py
waha/exceptions.py
waha/http_client.py
waha/types.py
waha/namespaces/__init__.py
waha/namespaces/auth.py
waha/namespaces/channels.py
waha/namespaces/chats.py
waha/namespaces/contacts.py
waha/namespaces/groups.py
waha/namespaces/labels.py
waha/namespaces/media.py
waha/namespaces/messages.py
waha/namespaces/presence.py
waha/namespaces/profile.py
waha/namespaces/sessions.py
waha/namespaces/status.py
waha-1.0.5.dist-info/METADATA
waha-1.0.5.dist-info/WHEEL
waha-1.0.5.dist-info/licenses/LICENSE
waha-1.0.5.dist-info/RECORD
