Metadata-Version: 2.4
Name: waha
Version: 1.0.5
Summary: Python package for WAHA (WhatsApp HTTP API)
Project-URL: Homepage, https://github.com/devlikeapro/waha-python
Project-URL: Documentation, https://waha.devlike.pro
Project-URL: Repository, https://github.com/devlikeapro/waha-python
Project-URL: Bug Tracker, https://github.com/devlikeapro/waha-python/issues
Project-URL: Changelog, https://github.com/devlikeapro/waha-python/blob/main/CHANGELOG.md
Author-email: Majid Al-Raimi <majidsraimi@gmail.com>
License-Expression: MIT
License-File: LICENSE
Keywords: api,chatbot,messaging,sdk,waha,whatsapp
Classifier: Development Status :: 4 - Beta
Classifier: Intended Audience :: Developers
Classifier: License :: OSI Approved :: MIT License
Classifier: Operating System :: OS Independent
Classifier: Programming Language :: Python :: 3
Classifier: Programming Language :: Python :: 3.8
Classifier: Programming Language :: Python :: 3.9
Classifier: Programming Language :: Python :: 3.10
Classifier: Programming Language :: Python :: 3.11
Classifier: Programming Language :: Python :: 3.12
Classifier: Topic :: Communications :: Chat
Classifier: Topic :: Internet :: WWW/HTTP
Classifier: Topic :: Software Development :: Libraries :: Python Modules
Classifier: Typing :: Typed
Requires-Python: >=3.8
Requires-Dist: httpx<1.0.0,>=0.24.0
Requires-Dist: pydantic<3.0.0,>=2.0.0
Provides-Extra: dev
Requires-Dist: black>=23.0.0; extra == 'dev'
Requires-Dist: flake8>=6.0.0; extra == 'dev'
Requires-Dist: isort>=5.12.0; extra == 'dev'
Requires-Dist: mypy>=1.0.0; extra == 'dev'
Requires-Dist: pre-commit>=3.0.0; extra == 'dev'
Requires-Dist: pytest-asyncio>=0.20.0; extra == 'dev'
Requires-Dist: pytest-cov>=4.0.0; extra == 'dev'
Requires-Dist: pytest>=7.0.0; extra == 'dev'
Provides-Extra: docs
Requires-Dist: mkdocs-material>=8.0.0; extra == 'docs'
Requires-Dist: mkdocs>=1.4.0; extra == 'docs'
Requires-Dist: mkdocstrings[python]>=0.20.0; extra == 'docs'
Provides-Extra: examples
Requires-Dist: pillow>=9.0.0; extra == 'examples'
Requires-Dist: python-dotenv>=1.0.0; extra == 'examples'
